example_os_linzy/__init__.py
example_os_linzy/example.py
example_os_linzy-0.0.3.dist-info/LICENSE
example_os_linzy-0.0.3.dist-info/METADATA
example_os_linzy-0.0.3.dist-info/WHEEL
example_os_linzy-0.0.3.dist-info/top_level.txt
example_os_linzy-0.0.3.dist-info/RECORD
