Metadata-Version: 2.1
Name: example-os-linzy
Version: 0.0.3
Summary: 测试项目
Author: os_linzy
Author-email: 1269125170@gmail.com
Classifier: Programming Language :: Python :: 3
Classifier: License :: OSI Approved :: MIT License
Classifier: Operating System :: OS Independent
Requires-Python: >=3.6
License-File: LICENSE
